<?xml version="1.0" encoding="utf-8"?>
<mission id="dlcDemoIntro1">
  <goals>
    <goal type="filedownload" target="dDemointro1" file="FTPSprint.exe" path="bin"/>
  </goals>
  <nextMission>../DLC/Missions/Demo/DLCDemoIntroMission2.xml</nextMission>
  <email>
    <sender>Matt            .</sender>
    <subject>상황 정리</subject>
    <body>안녕,
    
돌아온 걸 환영해. 새로운 건수가 생겨서 많은 그룹에서 관심을 보이고 있어. Entropy와 CSEC 둘 다 에이전트를 그 쪽에 붙였긴 한데, 너도 관심이 있을 것 같아서.

우선은 상황 설명부터 하도록 하지. 이 VM에는 SSHCrack과 FTPBounce가 미리 로딩되어 있을 거야. 연결된 서버에 침입해서 ~/bin에 있는 파일을 다운로드하면 돼. 마음에 들 거야.

이걸 끝내면, Tex로부터 전달할 게 있어.
네가 녹슬지 않았으면 좋겠군. 실력이 필요할 테니까.
-Matt
    </body>
    <attachments>
      <link comp="dDemointro1" />
      <note title="Recap">다음으로 프로그램을 실행:
ProgramName [PortNumber]
포트가 열리면 "Porthack"으로 활성 보안을 해제할 것.

타겟 컴퓨터의 bin/XXXX을(를) 다운로드하고 메일에 답장한다.
- scp [filename]

/log의 로그를 삭제한다
-rm [* or filename]
</note>
    </attachments>
  </email>
</mission>