<?xml version="1.0" encoding="utf-8"?>
<Computer id="dpae_psy_1" name="Faith Morello's Laptop" security="3" ip="209.68.11.125" type="4" icon="DLCLaptop">
  
  <!-- Home comp of someone who works at Psylance, contracting out to the airport
  Goes by NAME_WIP on the IRC chat of Psylance employees. 
  
  Has File downloaded form the Internet describing how to speed up torrents (opening torrent port),
  contains some sort of example with port numbers, and they've changed the port to match it exactly
  
  This needs to contain the username and password used for the IRC server on it (but not an IP link to the server itself).
  Perhaps write a file about it always being open, so they never have to reconnect to it or something?
  -->

  <firewall level="-1"/>
  <trace time="-1" />
  <portsForCrack val="3" />
  <ports>21, 443, 6881, 80</ports>
  <portRemap>21=1887,6881=8,80=8080</portRemap>

  <positionNear target="dpa_whitelist" position="240" total="360" extraDistance="0"/>

  <customthemefile path="sys" name="RTClassic_x-server.sys" themePath="DLC/Themes/RiptideClassicTheme.xml"/>
  <customthemefile path="sys" name="x-server.sys" themePath="DLC/Themes/RiptideClassicTheme.xml"/>
  
  
  <file path="home/torrents" name="guide.txt">PortSmacker 사용자 가이드

PortSmacker는 비전통적인 포트를 사용하여 ISP 수준 NAT 쓰로틀링 및 방화벽을 돌파함으로써 토렌트 속도를 높이기 위한 도구입니다.

사용자 인터페이스는 스프레드시트와 유사합니다. 설정을 변경하려면 셀에 숫자를 입력하고 Enter 키를 치십시오. 이 도구는 고급 사용자를 위한 것이니, 함부로 손대지 마십시오.

사용 예시:

토렌트 속도를 올리고 싶은데,  내 ISP가 포트 6881을 쓰로틀링하고 있음. 쓰로틀링을 피하려고 포트 8로 우회했더니 왜 그런지는 모르지만 훨씬 잘 됨. 결국 ISP가 알아채고 포트 8을 쓰로틀링하기 시작하지만, 그 때까지는 계속 사용하기에 괜찮음.
  </file>

    <file path="home/torrents" name="HackerCracker_Cracked_NoDVD.zip">#BINARY#</file>

    <file path="home/torrents" name="PortSmacker.zip">#BINARY#</file>

    <file path="home/torrents" name="DIY_Pickles_A_Guide_To_Pickling_In_The.zip">#BINARY#</file>

    <file path="home/torrents" name="VRDesk.zip">#BINARY#</file>

  <file path="home/torrents" name="PacificPortcrusher.exe">#PACIFIC_EXE#</file>
  <file path="bin" name="PacificPortcrusher.exe">#PACIFIC_EXE#</file>


  <!-- Translators: DO NOT TRANSLATE THE NAME OR PASSWORD HERE -->
    <file path="home/work" name="logindetails.txt">> dardour@psylance.net이 보냄:
> 이봐 Faith,
> 이건 자네 IRC 로그인 세부정보야.
> 기회 있을 때 변경하는 거 잊지 말고. NickServ를 통해서. 물론 재접속할 필요는 없어.
> -Darryl

> IRC 사용자명: faithless
> 암호: catsarebestpet</file>
  
</Computer>